MANIFEST.in
README.md
requirements.txt
setup.cfg
setup.py
envirocar/__init__.py
envirocar/exceptions.py
envirocar/client/__init__.py
envirocar/client/client_config.py
envirocar/client/download_client.py
envirocar/client/request_param.py
envirocar/client/utils.py
envirocar/client/api/__init__.py
envirocar/client/api/track_api.py
envirocar_py.egg-info/PKG-INFO
envirocar_py.egg-info/SOURCES.txt
envirocar_py.egg-info/dependency_links.txt
envirocar_py.egg-info/requires.txt
envirocar_py.egg-info/top_level.txt