Metadata-Version: 2.1
Name: envirocar-py
Version: 0.0.3
Summary: Python Utilities for enviroCar
Home-page: https://github.com/enviroCar/envirocar-py
License: MIT
Keywords: enviroCar,trajectory,xFCD
Platform: UNKNOWN
Classifier: Development Status :: 3 - Alpha
Classifier: License :: OSI Approved :: MIT License
Classifier: Programming Language :: Python :: 3
Classifier: Programming Language :: Python :: 3.6
Classifier: Programming Language :: Python :: 3.7
Classifier: Programming Language :: Python :: 3.8
